cliLoader/__init__.py
cliLoader/components/__init__.py
cliLoader/components/loader/__init__.py
cliLoader/components/loader/config.py
cliLoader/components/loader/loader.py
cliLoader-0.1.0.dist-info/METADATA
cliLoader-0.1.0.dist-info/WHEEL
cliLoader-0.1.0.dist-info/top_level.txt
cliLoader-0.1.0.dist-info/RECORD
