Metadata-Version: 2.1
Name: cliLoader
Version: 0.1.0
Summary: a simple generic colorful CLI progress bar
Home-page: https://github.com/itay-bardugo/cliLoader
Author: Itay Bardugo
Author-email: itaybardugo91@gmail.com
License: UNKNOWN
Platform: UNKNOWN
Classifier: Programming Language :: Python :: 3
Classifier: License :: OSI Approved :: MIT License
Classifier: Operating System :: OS Independent
